{
    "backend": "api-server-nodejs",
    "db_name": "",
    "db_pass": "",
    "db_type": "sqlite",
    "db_user": "",
    "dbms": "1",
    "description": "generated product",
    "design": "soft-ui-dashboard",
    "docker": "0",
    "err_code": 0,
    "frontend": "react",
    "heroku": "0",
    "pattern": "fullstack",
    "pro": "0",
    "task_id": "42291ffc-6545-467e-bb84-85b492836428",
    "task_info": "Upload Sources [0%] - 290 files",
    "task_output": "42291ffc-6545-467e-bb84-85b492836428.zip",
    "task_result": "SUCCESS",
    "task_state": "RUNNING",
    "task_ts_end": "2022-11-29-17-45-27",
    "task_ts_start": "2022-11-29-17-45-25"
}